AUTHORS.rst
CONTRIBUTING.rst
HISTORY.rst
LICENSE
MANIFEST.in
README.rst
setup.cfg
setup.py
docs/Makefile
docs/conf.py
docs/index.rst
docs/make.bat
docs/readme.rst
docs/_build/html/_static/ajax-loader.gif
docs/_build/html/_static/comment-bright.png
docs/_build/html/_static/comment-close.png
docs/_build/html/_static/comment.png
docs/_build/html/_static/down-pressed.png
docs/_build/html/_static/down.png
docs/_build/html/_static/file.png
docs/_build/html/_static/minus.png
docs/_build/html/_static/plus.png
docs/_build/html/_static/up-pressed.png
docs/_build/html/_static/up.png
docs/_build/singlehtml/_static/ajax-loader.gif
docs/_build/singlehtml/_static/comment-bright.png
docs/_build/singlehtml/_static/comment-close.png
docs/_build/singlehtml/_static/comment.png
docs/_build/singlehtml/_static/down-pressed.png
docs/_build/singlehtml/_static/down.png
docs/_build/singlehtml/_static/file.png
docs/_build/singlehtml/_static/minus.png
docs/_build/singlehtml/_static/plus.png
docs/_build/singlehtml/_static/up-pressed.png
docs/_build/singlehtml/_static/up.png
nordvpn_converter/__init__.py
nordvpn_converter/cli.py
nordvpn_converter/converter.py
nordvpn_converter.egg-info/PKG-INFO
nordvpn_converter.egg-info/SOURCES.txt
nordvpn_converter.egg-info/dependency_links.txt
nordvpn_converter.egg-info/entry_points.txt
nordvpn_converter.egg-info/not-zip-safe
nordvpn_converter.egg-info/top_level.txt
nordvpn_converter/data/nm_template
tests/test_converter.py
tests/test_nordvpn_converter.py