Metadata-Version: 1.1
Name: nordvpn-converter
Version: 1.0.1
Summary: Conversion tool from OVPN files into NetworkManager compatible. 
Home-page: https://bitbucket.org/cnavalici/nordvpn-converter/
Author: Cristian Năvălici
Author-email: cristian.navalici@gmail.com
License: GNU General Public License v3
Keywords: nordvpn_converter
Platform: UNKNOWN
Classifier: Development Status :: 5 - Production/Stable
Classifier: Intended Audience :: End Users/Desktop
Classifier: License :: OSI Approved :: GNU General Public License v3 (GPLv3)
Classifier: Natural Language :: English
Classifier: Programming Language :: Python :: 3
Classifier: Programming Language :: Python :: 3.3
Classifier: Programming Language :: Python :: 3.4
Classifier: Programming Language :: Python :: 3.5
